{"_path":"/","_dir":"","_draft":false,"_partial":false,"_locale":"","title":"Hajisky","description":"What i'm all about","head":{"meta":[{"name":"robots","content":"index, follow"},{"name":"author","content":"Haji Mmohammed"},{"name":"copyright","content":"© 2022 Haji Mmohammed"}]},"body":{"type":"root","children":[{"type":"element","tag":"main-title","props":{},"children":[{"type":"element","tag":"p","props":{},"children":[{"type":"text","value":"Hi, "},{"type":"element","tag":"span","props":{"className":["text-primary"]},"children":[{"type":"text","value":"I'm Haji"}]},{"type":"text","value":". I bring Ideas to life"}]},{"type":"element","tag":"template","props":{"v-slot:details":""},"children":[{"type":"element","tag":"p","props":{},"children":[{"type":"text","value":"Product Developer, Vue & Nuxt Enthusiast"}]}]}]},{"type":"element","tag":"h2","props":{"id":"recent-blog-posts"},"children":[{"type":"text","value":"Recent Blog Posts"}]},{"type":"element","tag":"recent-blogs","props":{},"children":[]},{"type":"element","tag":"h2","props":{"id":"recent-projects"},"children":[{"type":"text","value":"Recent Projects"}]},{"type":"element","tag":"recent-projects","props":{},"children":[]}],"toc":{"title":"","searchDepth":2,"depth":2,"links":[{"id":"recent-blog-posts","depth":2,"text":"Recent Blog Posts"},{"id":"recent-projects","depth":2,"text":"Recent Projects"}]}},"_type":"markdown","_id":"content:index.md","_source":"content","_file":"index.md","_extension":"md"}